README.md
setup.py
scratchlink/Cloud.py
scratchlink/Exceptions.py
scratchlink/Forum.py
scratchlink/FrontPage.py
scratchlink/Project.py
scratchlink/ScratchLink.py
scratchlink/Studio.py
scratchlink/User.py
scratchlink/__init__.py
scratchlink.egg-info/PKG-INFO
scratchlink.egg-info/SOURCES.txt
scratchlink.egg-info/dependency_links.txt
scratchlink.egg-info/requires.txt
scratchlink.egg-info/top_level.txt