Metadata-Version: 2.1
Name: scratchlink
Version: 1.0.1
Summary: ScratchLink is a simple Python Library to get the data of Scratch using the Scratch API. This library is simple to use. This library need no login!
Home-page: https://github.com/Sid72020123/scratchlink/
Author: Siddhesh Chavan
Author-email: siddheshchavan2020@gmail.com
License: MIT
Keywords: connect-scratch scratch-api api
Platform: UNKNOWN
Classifier: Development Status :: 5 - Production/Stable
Classifier: Intended Audience :: Education
Classifier: Operating System :: OS Independent
Classifier: License :: OSI Approved :: MIT License
Classifier: Programming Language :: Python :: 3
